hec/__init__.py
hec/const.py
hec/datastore.py
hec/duration.py
hec/hectime.py
hec/interval.py
hec/location.py
hec/parameter.py
hec/quality.py
hec/rounding.py
hec/shared.py
hec/timeseries.py
hec/timespan.py
hec/unit.py
hec/rating/__init__.py
hec/rating/abstract_rating.py
hec/rating/abstract_rating_set.py
hec/rating/local_rating_set.py
hec/rating/paired_data.py
hec/rating/paired_data_rating.py
hec/rating/rating_shared.py
hec/rating/rating_specification.py
hec/rating/rating_template.py
hec/rating/reference_rating_set.py
hec/rating/simple_rating.py
hec/rating/table_rating.py
hec/resources/base_parameters.tsv
hec_python_library-1.0.dist-info/licenses/LICENSE
hec_python_library-1.0.dist-info/METADATA
hec_python_library-1.0.dist-info/WHEEL
hec_python_library-1.0.dist-info/top_level.txt
hec_python_library-1.0.dist-info/RECORD
