Metadata-Version: 2.4
Name: hec-python-library
Version: 1.0
Summary: Python 3 implementation of HEC Java/Jython utility classes
Author-email: Michael Perryman <michael.d.perryman@usace.army.mil>
License: MIT License
Keywords: HEC,timeseries,time series,DSS,HEC-DSS,CWMS
Classifier: Programming Language :: Python :: 3
Classifier: Operating System :: OS Independent
Requires-Python: >=3.9
License-File: LICENSE
Requires-Dist: lxml>=6.0.0
Requires-Dist: numpy>=1.26.4
Requires-Dist: pandas>=2.2.2
Requires-Dist: Pint>=0.24.3
Requires-Dist: Pint-pandas>=0.6.2
Requires-Dist: tzlocal>=5.2
Provides-Extra: docs
Requires-Dist: sphinx; extra == "docs"
Requires-Dist: sphinx_rtd_theme; extra == "docs"
Requires-Dist: sphinx-design; extra == "docs"
Dynamic: license-file
